[
  {
    "type": "MOD_INFO",
    "id": "mom_increase_power_learn_delay",
    "name": "Mind Over Matter: <color_magenta>Increase Random Delay Before Learning New Powers</color>",
    "authors": [ "Standing-Storm" ],
    "description": "<color_red>Increases Difficulty!</color>  Change the 12 to 168 hour delay before becoming eligible to learn a new power to 7 days to 30 days.  If you play with greatly-decreased skill gain or love long games, use this.",
    "category": "misc_additions",
    "dependencies": [ "dda", "mindovermatter" ]
  },
  {
    "type": "effect_on_condition",
    "id": "EOC_MOM_SUBMOD_GAMESTART_INSIGHT_VARIABLES",
    "eoc_type": "EVENT",
    "required_event": "game_begin",
    "effect": [
      { "math": [ "global_insight_power_learning_time_low", "=", "604800" ] },
      { "math": [ "global_insight_power_learning_time_high", "=", "2592000" ] }
    ]
  }
]
